bayes_mapvar/__init__.py
bayes_mapvar/exceptions.py
bayes_mapvar/map_utils.py
bayes_mapvar/mapvar.py
bayes_mapvar/var_utils.py
bayes_mapvar-0.0.2.dist-info/LICENSE.txt
bayes_mapvar-0.0.2.dist-info/METADATA
bayes_mapvar-0.0.2.dist-info/WHEEL
bayes_mapvar-0.0.2.dist-info/top_level.txt
bayes_mapvar-0.0.2.dist-info/RECORD
